tg_file_id
